geo_roughness_tool/__init__.py
geo_roughness_tool/cli_main.py
geo_roughness_tool/gui_main.py
geo_roughness_tool/log_config.py
geo_roughness_tool/main.py
geo_roughness_tool/classes/__init__.py
geo_roughness_tool/classes/application_driver.py
geo_roughness_tool/classes/defaults.py
geo_roughness_tool/classes/geo_tiff_processor.py
geo_roughness_tool/classes/processing_parameters.py
geo_roughness_tool/classes/threshold_optimizer.py
geo_roughness_tool/gui/__init__.py
geo_roughness_tool/gui/analyze_and_optimize.py
geo_roughness_tool/gui/defaults.py
geo_roughness_tool/gui/footer_frame.py
geo_roughness_tool/gui/parameter_input.py
geo_roughness_tool/gui/path_frame.py
geo_roughness_tool/gui/preview_image.py
geo_roughness_tool/gui/resources/GeoRoughness_Banner_long_dark.png
geo_roughness_tool/gui/resources/GeoRoughness_Banner_long_light.png
geo_roughness_tool/gui/resources/app_icon_dark.ico
geo_roughness_tool/gui/resources/app_icon_dark.png
geo_roughness_tool/gui/resources/app_icon_light.png
geo_roughness_tool-0.4.31.post1.dist-info/LICENSE
geo_roughness_tool-0.4.31.post1.dist-info/METADATA
geo_roughness_tool-0.4.31.post1.dist-info/WHEEL
geo_roughness_tool-0.4.31.post1.dist-info/entry_points.txt
geo_roughness_tool-0.4.31.post1.dist-info/top_level.txt
geo_roughness_tool-0.4.31.post1.dist-info/RECORD
