Metadata-Version: 2.1
Name: geo-roughness-tool
Version: 0.4.31.post1
Summary: A package for calculating surface roughness using GeoTIFF DEM files with a GUI and CLI
Home-page: https://github.com/lbatschelet/GeoRoughness-Tool
Author: Lukas Batschelet
License: MIT
Project-URL: Documentation, https://github.com/lbatschelet/GeoRoughness-Tool/wiki
Project-URL: Source, https://github.com/lbatschelet/GeoRoughness-Tool
Project-URL: Tracker, https://github.com/lbatschelet/GeoRoughness-Tool/issues
Keywords: GIS,GeoTIFF,DEM,surface roughness,geographic information systems
Classifier: Development Status :: 4 - Beta
Classifier: Intended Audience :: Science/Research
Classifier: License :: OSI Approved :: MIT License
Classifier: Operating System :: OS Independent
Classifier: Programming Language :: Python :: 3
Classifier: Programming Language :: Python :: 3.12
Classifier: Topic :: Scientific/Engineering :: GIS
Requires-Python: >=3.12
License-File: LICENSE
Requires-Dist: customtkinter ==5.2.2
Requires-Dist: matplotlib ==3.8.4
Requires-Dist: numpy ==1.26.4
Requires-Dist: Pillow ==10.3.0
Requires-Dist: rasterio ==1.3.10
Requires-Dist: screeninfo ==0.8.1
Requires-Dist: setuptools ==69.5.1
Requires-Dist: requests ==2.32.2
Requires-Dist: packaging ==24.0
Requires-Dist: wheel ==0.43.0
Requires-Dist: twine ==5.1.0
Requires-Dist: setuptools-scm ==8.1.0
